plotstring/__init__.py
plotstring/src/__init__.py
plotstring/src/plotstring.py
plotstring/test/__init__.py
plotstring/test/test_plotstring.py
plotstring-0.0.16.dist-info/LICENSE
plotstring-0.0.16.dist-info/METADATA
plotstring-0.0.16.dist-info/WHEEL
plotstring-0.0.16.dist-info/top_level.txt
plotstring-0.0.16.dist-info/RECORD
