Metadata-Version: 2.1
Name: plotstring
Version: 0.0.16
Summary: Create a plot of the data in the clipboard AS STRING. The plot can be used as a normal string in comments, bloc-notes, ... 
Home-page: https://github.com/bouz1/PypiContributions/tree/main/Plot_AS_String
Author: Abb BOZZ
Author-email: bozzabb1@gmail.com
License: MIT
Platform: UNKNOWN
Classifier: License :: OSI Approved :: MIT License
Classifier: Programming Language :: Python :: 3.10
Classifier: Operating System :: OS Independent
Requires-Python: >=3.1
License-File: LICENSE
Provides-Extra: dev
Requires-Dist: pyperclip ; extra == 'dev'
Requires-Dist: pandas ; extra == 'dev'
Requires-Dist: numpy ; extra == 'dev'
